easier_python_client/__init__.py
easier_python_client/client.py
tests/__init__.py
tests/tests.py
easier_python_client-0.1.4.dist-info/LICENSE
easier_python_client-0.1.4.dist-info/METADATA
easier_python_client-0.1.4.dist-info/WHEEL
easier_python_client-0.1.4.dist-info/top_level.txt
easier_python_client-0.1.4.dist-info/RECORD
