Metadata-Version: 2.1
Name: easier-python-client
Version: 0.1.4
Summary: The EASIER Data Initiative Python IPFS Client
Home-page: UNKNOWN
Author: The EASIER Data Initiative
License: MIT
Platform: UNKNOWN
License-File: LICENSE
Requires-Dist: ipfsspec
Requires-Dist: fsspec
Requires-Dist: requests
Requires-Dist: pandas
Requires-Dist: beautifulsoup4
Requires-Dist: pystac-client
